{
    "classes": [
        {
            "color": [
                0,
                255,
                0
            ],
            "id": 0,
            "name": "NORMAL"
        },
        {
            "color": [
                0,
                0,
                255
            ],
            "id": 1,
            "name": "NODAL",
            "severities": [
                100,
                75,
                50
            ]
        },
        {
            "color": [
                255,
                0,
                0
            ],
            "id": 2,
            "name": "BMP",
            "severities": [
                100,
                75,
                50
            ]
        },
        {
            "color": [
                0,
                255,
                255
            ],
            "id": 3,
            "name": "WNT"
        },
        {
            "color": [
                255,
                255,
                0
            ],
            "id": 4,
            "name": "FGF"
        },
        {
            "color": [
                255,
                128,
                128
            ],
            "id": 5,
            "name": "SHH"
        },
        {
            "color": [
                0,
                128,
                255
            ],
            "id": 6,
            "name": "PCP"
        },
        {
            "color": [
                128,
                0,
                128
            ],
            "id": 7,
            "name": "RA"
        },
        {
            "color": [
                255,
                0,
                255
            ],
            "id": 8,
            "name": "BOOM"
        },
        {
            "color": [
                0,
                0,
                0
            ],
            "id": 9,
            "name": "UNKNOWN"
        }
    ],
    "detection_list": [
        {
            "brx": 1843,
            "bry": 1594,
            "classId": 3,
            "className": "UNKNOWN",
            "confidence": true,
            "id": 1,
            "oldProbs": [
                4.170192335383931e-29,
                1.1630777253895982e-43,
                1.586860348028141e-27,
                3.0700207275813822e-40,
                0.0,
                0.0,
                8.948243577669698e-40,
                1.747404331249325e-38,
                1.144706500735321e-36,
                1.2879734366126175e-23,
                2.29986328005664e-37,
                2.735143928913145e-34,
                2.432286184821032e-32,
                1.0
            ],
            "prob": [
                9.999999717180685e-10,
                9.999999717180685e-10,
                9.999999717180685e-10,
                9.999999717180685e-10,
                9.999999717180685e-10,
                9.999999717180685e-10,
                9.999999717180685e-10,
                9.999999717180685e-10,
                9.999999717180685e-10,
                1.0
            ],
            "severe": 100,
            "severityProbs": [
                [
                    100,
                    9.999999717180685e-10
                ],
                [
                    100,
                    9.999999717180685e-10
                ],
                [
                    75,
                    9.999999717180685e-10
                ],
                [
                    50,
                    9.999999717180685e-10
                ],
                [
                    100,
                    9.999999717180685e-10
                ],
                [
                    75,
                    9.999999717180685e-10
                ],
                [
                    50,
                    9.999999717180685e-10
                ],
                [
                    100,
                    9.999999717180685e-10
                ],
                [
                    100,
                    9.999999717180685e-10
                ],
                [
                    100,
                    9.999999717180685e-10
                ],
                [
                    100,
                    9.999999717180685e-10
                ],
                [
                    100,
                    9.999999717180685e-10
                ],
                [
                    100,
                    9.999999717180685e-10
                ],
                [
                    100,
                    1.0
                ]
            ],
            "tlx": 1469,
            "tly": 1220
        },
        {
            "brx": 1518,
            "bry": 1774,
            "classId": 3,
            "className": "UNKNOWN",
            "confidence": true,
            "id": 2,
            "oldProbs": [
                0.0,
                0.0,
                0.0,
                0.0,
                0.0,
                0.0,
                0.0,
                0.0,
                4.484155085839415e-44,
                2.9912257375019697e-27,
                0.0,
                0.0,
                7.286752014489049e-44,
                1.0
            ],
            "prob": [
                9.999999717180685e-10,
                9.999999717180685e-10,
                9.999999717180685e-10,
                9.999999717180685e-10,
                9.999999717180685e-10,
                9.999999717180685e-10,
                9.999999717180685e-10,
                9.999999717180685e-10,
                9.999999717180685e-10,
                1.0
            ],
            "severe": 100,
            "severityProbs": [
                [
                    100,
                    9.999999717180685e-10
                ],
                [
                    100,
                    9.999999717180685e-10
                ],
                [
                    75,
                    9.999999717180685e-10
                ],
                [
                    50,
                    9.999999717180685e-10
                ],
                [
                    100,
                    9.999999717180685e-10
                ],
                [
                    75,
                    9.999999717180685e-10
                ],
                [
                    50,
                    9.999999717180685e-10
                ],
                [
                    100,
                    9.999999717180685e-10
                ],
                [
                    100,
                    9.999999717180685e-10
                ],
                [
                    100,
                    9.999999717180685e-10
                ],
                [
                    100,
                    9.999999717180685e-10
                ],
                [
                    100,
                    9.999999717180685e-10
                ],
                [
                    100,
                    9.999999717180685e-10
                ],
                [
                    100,
                    1.0
                ]
            ],
            "tlx": 1119,
            "tly": 1375
        },
        {
            "brx": 1519,
            "bry": 1268,
            "classId": 3,
            "className": "UNKNOWN",
            "confidence": true,
            "id": 3,
            "oldProbs": [
                4.501645541791788e-32,
                1.2492458306655875e-34,
                5.284317951678602e-28,
                2.3709704893038215e-32,
                0.0,
                0.0,
                1.680741365399289e-32,
                1.6734528596138094e-33,
                1.7586881019287273e-32,
                3.6001306761329536e-26,
                2.764246964987597e-32,
                5.28775386242114e-32,
                1.0713787426957238e-25,
                1.0
            ],
            "prob": [
                9.999999717180685e-10,
                9.999999717180685e-10,
                9.999999717180685e-10,
                9.999999717180685e-10,
                9.999999717180685e-10,
                9.999999717180685e-10,
                9.999999717180685e-10,
                9.999999717180685e-10,
                9.999999717180685e-10,
                1.0
            ],
            "severe": 100,
            "severityProbs": [
                [
                    100,
                    9.999999717180685e-10
                ],
                [
                    100,
                    9.999999717180685e-10
                ],
                [
                    75,
                    9.999999717180685e-10
                ],
                [
                    50,
                    9.999999717180685e-10
                ],
                [
                    100,
                    9.999999717180685e-10
                ],
                [
                    75,
                    9.999999717180685e-10
                ],
                [
                    50,
                    9.999999717180685e-10
                ],
                [
                    100,
                    9.999999717180685e-10
                ],
                [
                    100,
                    9.999999717180685e-10
                ],
                [
                    100,
                    9.999999717180685e-10
                ],
                [
                    100,
                    9.999999717180685e-10
                ],
                [
                    100,
                    9.999999717180685e-10
                ],
                [
                    100,
                    9.999999717180685e-10
                ],
                [
                    100,
                    1.0
                ]
            ],
            "tlx": 1141,
            "tly": 890
        },
        {
            "brx": 1155,
            "bry": 1138,
            "classId": 3,
            "className": "UNKNOWN",
            "confidence": true,
            "id": 4,
            "oldProbs": [
                1.1386355905829886e-26,
                9.004735802874935e-34,
                5.282466571462504e-22,
                3.7526786887603244e-39,
                5.387992595328922e-41,
                1.4977326857310909e-37,
                1.0260101196519476e-30,
                2.575932805250697e-29,
                5.6599582794352815e-31,
                8.515414047101411e-21,
                1.0673757419878896e-23,
                3.179583949030726e-29,
                7.768413408416341e-21,
                1.0
            ],
            "prob": [
                9.999999717180685e-10,
                9.999999717180685e-10,
                9.999999717180685e-10,
                9.999999717180685e-10,
                9.999999717180685e-10,
                9.999999717180685e-10,
                9.999999717180685e-10,
                9.999999717180685e-10,
                9.999999717180685e-10,
                1.0
            ],
            "severe": 100,
            "severityProbs": [
                [
                    100,
                    9.999999717180685e-10
                ],
                [
                    100,
                    9.999999717180685e-10
                ],
                [
                    75,
                    9.999999717180685e-10
                ],
                [
                    50,
                    9.999999717180685e-10
                ],
                [
                    100,
                    9.999999717180685e-10
                ],
                [
                    75,
                    9.999999717180685e-10
                ],
                [
                    50,
                    9.999999717180685e-10
                ],
                [
                    100,
                    9.999999717180685e-10
                ],
                [
                    100,
                    9.999999717180685e-10
                ],
                [
                    100,
                    9.999999717180685e-10
                ],
                [
                    100,
                    9.999999717180685e-10
                ],
                [
                    100,
                    9.999999717180685e-10
                ],
                [
                    100,
                    9.999999717180685e-10
                ],
                [
                    100,
                    1.0
                ]
            ],
            "tlx": 769,
            "tly": 752
        },
        {
            "brx": 683,
            "bry": 1011,
            "classId": 3,
            "className": "UNKNOWN",
            "confidence": true,
            "id": 5,
            "oldProbs": [
                2.6613245001364e-23,
                1.774328134736059e-26,
                7.052767782297702e-26,
                1.5815932658216263e-32,
                3.783505853677006e-43,
                1.087407608316058e-42,
                6.535515558000418e-35,
                1.473774631750222e-30,
                1.154019103467793e-30,
                1.2465636064981135e-20,
                3.043663808887978e-33,
                1.0668402106311492e-30,
                2.249656777890187e-20,
                1.0
            ],
            "prob": [
                9.999999717180685e-10,
                9.999999717180685e-10,
                9.999999717180685e-10,
                9.999999717180685e-10,
                9.999999717180685e-10,
                9.999999717180685e-10,
                9.999999717180685e-10,
                9.999999717180685e-10,
                9.999999717180685e-10,
                1.0
            ],
            "severe": 100,
            "severityProbs": [
                [
                    100,
                    9.999999717180685e-10
                ],
                [
                    100,
                    9.999999717180685e-10
                ],
                [
                    75,
                    9.999999717180685e-10
                ],
                [
                    50,
                    9.999999717180685e-10
                ],
                [
                    100,
                    9.999999717180685e-10
                ],
                [
                    75,
                    9.999999717180685e-10
                ],
                [
                    50,
                    9.999999717180685e-10
                ],
                [
                    100,
                    9.999999717180685e-10
                ],
                [
                    100,
                    9.999999717180685e-10
                ],
                [
                    100,
                    9.999999717180685e-10
                ],
                [
                    100,
                    9.999999717180685e-10
                ],
                [
                    100,
                    9.999999717180685e-10
                ],
                [
                    100,
                    9.999999717180685e-10
                ],
                [
                    100,
                    1.0
                ]
            ],
            "tlx": 292,
            "tly": 620
        },
        {
            "brx": 952,
            "bry": 1793,
            "classId": 3,
            "className": "UNKNOWN",
            "confidence": true,
            "id": 6,
            "oldProbs": [
                0.0,
                0.0,
                0.0,
                0.0,
                0.0,
                0.0,
                0.0,
                0.0,
                0.0,
                0.0,
                0.0,
                0.0,
                0.0,
                1.0
            ],
            "prob": [
                9.999999717180685e-10,
                9.999999717180685e-10,
                9.999999717180685e-10,
                9.999999717180685e-10,
                9.999999717180685e-10,
                9.999999717180685e-10,
                9.999999717180685e-10,
                9.999999717180685e-10,
                9.999999717180685e-10,
                1.0
            ],
            "severe": 100,
            "severityProbs": [
                [
                    100,
                    9.999999717180685e-10
                ],
                [
                    100,
                    9.999999717180685e-10
                ],
                [
                    75,
                    9.999999717180685e-10
                ],
                [
                    50,
                    9.999999717180685e-10
                ],
                [
                    100,
                    9.999999717180685e-10
                ],
                [
                    75,
                    9.999999717180685e-10
                ],
                [
                    50,
                    9.999999717180685e-10
                ],
                [
                    100,
                    9.999999717180685e-10
                ],
                [
                    100,
                    9.999999717180685e-10
                ],
                [
                    100,
                    9.999999717180685e-10
                ],
                [
                    100,
                    9.999999717180685e-10
                ],
                [
                    100,
                    9.999999717180685e-10
                ],
                [
                    100,
                    9.999999717180685e-10
                ],
                [
                    100,
                    1.0
                ]
            ],
            "tlx": 562,
            "tly": 1403
        },
        {
            "brx": 1392,
            "bry": 824,
            "classId": 3,
            "className": "UNKNOWN",
            "confidence": true,
            "id": 7,
            "oldProbs": [
                1.38337024937108e-27,
                8.407790785948902e-45,
                3.007528699283968e-35,
                1.564992657837262e-37,
                0.0,
                0.0,
                4.8676705730827525e-29,
                4.3937430398718723e-35,
                1.5659860436547665e-33,
                3.5179536502543363e-19,
                5.353681463087008e-32,
                1.6745821607100642e-34,
                3.829646058721514e-25,
                1.0
            ],
            "prob": [
                9.999999717180685e-10,
                9.999999717180685e-10,
                9.999999717180685e-10,
                9.999999717180685e-10,
                9.999999717180685e-10,
                9.999999717180685e-10,
                9.999999717180685e-10,
                9.999999717180685e-10,
                9.999999717180685e-10,
                1.0
            ],
            "severe": 100,
            "severityProbs": [
                [
                    100,
                    9.999999717180685e-10
                ],
                [
                    100,
                    9.999999717180685e-10
                ],
                [
                    75,
                    9.999999717180685e-10
                ],
                [
                    50,
                    9.999999717180685e-10
                ],
                [
                    100,
                    9.999999717180685e-10
                ],
                [
                    75,
                    9.999999717180685e-10
                ],
                [
                    50,
                    9.999999717180685e-10
                ],
                [
                    100,
                    9.999999717180685e-10
                ],
                [
                    100,
                    9.999999717180685e-10
                ],
                [
                    100,
                    9.999999717180685e-10
                ],
                [
                    100,
                    9.999999717180685e-10
                ],
                [
                    100,
                    9.999999717180685e-10
                ],
                [
                    100,
                    9.999999717180685e-10
                ],
                [
                    100,
                    1.0
                ]
            ],
            "tlx": 1018,
            "tly": 450
        },
        {
            "brx": 1220,
            "bry": 1508,
            "classId": 3,
            "className": "UNKNOWN",
            "confidence": true,
            "id": 8,
            "oldProbs": [
                1.010191950064716e-34,
                3.6536054860340955e-41,
                1.68145413058367e-27,
                8.32369494146907e-37,
                1.6688063411644246e-40,
                0.0,
                1.0748106357710101e-38,
                1.9874157894921046e-38,
                3.313412073999601e-34,
                2.478684977890825e-24,
                6.371922293886518e-32,
                2.4167566701776013e-31,
                1.8068439360085698e-23,
                1.0
            ],
            "prob": [
                9.999999717180685e-10,
                9.999999717180685e-10,
                9.999999717180685e-10,
                9.999999717180685e-10,
                9.999999717180685e-10,
                9.999999717180685e-10,
                9.999999717180685e-10,
                9.999999717180685e-10,
                9.999999717180685e-10,
                1.0
            ],
            "severe": 100,
            "severityProbs": [
                [
                    100,
                    9.999999717180685e-10
                ],
                [
                    100,
                    9.999999717180685e-10
                ],
                [
                    75,
                    9.999999717180685e-10
                ],
                [
                    50,
                    9.999999717180685e-10
                ],
                [
                    100,
                    9.999999717180685e-10
                ],
                [
                    75,
                    9.999999717180685e-10
                ],
                [
                    50,
                    9.999999717180685e-10
                ],
                [
                    100,
                    9.999999717180685e-10
                ],
                [
                    100,
                    9.999999717180685e-10
                ],
                [
                    100,
                    9.999999717180685e-10
                ],
                [
                    100,
                    9.999999717180685e-10
                ],
                [
                    100,
                    9.999999717180685e-10
                ],
                [
                    100,
                    9.999999717180685e-10
                ],
                [
                    100,
                    1.0
                ]
            ],
            "tlx": 844,
            "tly": 1132
        },
        {
            "brx": 643,
            "bry": 1408,
            "classId": 3,
            "className": "UNKNOWN",
            "confidence": true,
            "id": 9,
            "oldProbs": [
                8.42645836169433e-24,
                2.2523297720885803e-25,
                2.3539065529178697e-26,
                1.108390371261165e-38,
                1.7877836057739216e-26,
                3.799282976677505e-35,
                1.859347464721858e-26,
                2.862218717981033e-30,
                2.2549734421972023e-25,
                2.5595632255574465e-20,
                6.718428069585308e-25,
                3.0234933224580574e-25,
                8.697751042617205e-15,
                1.0
            ],
            "prob": [
                9.999999717180685e-10,
                9.999999717180685e-10,
                9.999999717180685e-10,
                9.999999717180685e-10,
                9.999999717180685e-10,
                9.999999717180685e-10,
                9.999999717180685e-10,
                9.999999717180685e-10,
                9.999999717180685e-10,
                1.0
            ],
            "severe": 100,
            "severityProbs": [
                [
                    100,
                    9.999999717180685e-10
                ],
                [
                    100,
                    9.999999717180685e-10
                ],
                [
                    75,
                    9.999999717180685e-10
                ],
                [
                    50,
                    9.999999717180685e-10
                ],
                [
                    100,
                    9.999999717180685e-10
                ],
                [
                    75,
                    9.999999717180685e-10
                ],
                [
                    50,
                    9.999999717180685e-10
                ],
                [
                    100,
                    9.999999717180685e-10
                ],
                [
                    100,
                    9.999999717180685e-10
                ],
                [
                    100,
                    9.999999717180685e-10
                ],
                [
                    100,
                    9.999999717180685e-10
                ],
                [
                    100,
                    9.999999717180685e-10
                ],
                [
                    100,
                    9.999999717180685e-10
                ],
                [
                    100,
                    1.0
                ]
            ],
            "tlx": 251,
            "tly": 1016
        },
        {
            "brx": 1089,
            "bry": 522,
            "classId": 3,
            "className": "UNKNOWN",
            "confidence": true,
            "id": 10,
            "oldProbs": [
                4.84695125825311e-41,
                0.0,
                1.3135588234482009e-38,
                0.0,
                0.0,
                0.0,
                0.0,
                0.0,
                0.0,
                3.661500258166042e-24,
                0.0,
                9.374686726333026e-43,
                4.0637655465419695e-43,
                1.0
            ],
            "prob": [
                9.999999717180685e-10,
                9.999999717180685e-10,
                9.999999717180685e-10,
                9.999999717180685e-10,
                9.999999717180685e-10,
                9.999999717180685e-10,
                9.999999717180685e-10,
                9.999999717180685e-10,
                9.999999717180685e-10,
                1.0
            ],
            "severe": 100,
            "severityProbs": [
                [
                    100,
                    9.999999717180685e-10
                ],
                [
                    100,
                    9.999999717180685e-10
                ],
                [
                    75,
                    9.999999717180685e-10
                ],
                [
                    50,
                    9.999999717180685e-10
                ],
                [
                    100,
                    9.999999717180685e-10
                ],
                [
                    75,
                    9.999999717180685e-10
                ],
                [
                    50,
                    9.999999717180685e-10
                ],
                [
                    100,
                    9.999999717180685e-10
                ],
                [
                    100,
                    9.999999717180685e-10
                ],
                [
                    100,
                    9.999999717180685e-10
                ],
                [
                    100,
                    9.999999717180685e-10
                ],
                [
                    100,
                    9.999999717180685e-10
                ],
                [
                    100,
                    9.999999717180685e-10
                ],
                [
                    100,
                    1.0
                ]
            ],
            "tlx": 719,
            "tly": 152
        }
    ],
    "labeler": "default",
    "source_name": "-B003--PO01--LO016--CO6--SL001--PX32500--PW0100--IN0100--TM280--X053545--Y033148--Z190000--T3273048039--WE00010.jpg"
}